priv_goals/__init__.py
priv_goals/__main__.py
priv_goals/app.py
priv_goals/constants.py
priv_goals/exceptions.py
priv_goals/config/__init__.py
priv_goals/config/default_config.yaml
priv_goals/config/loader.py
priv_goals/config/validator.py
priv_goals/storage/__init__.py
priv_goals/storage/csv_storage.py
priv_goals/storage/goal.py
priv_goals/storage/goal_storage.py
priv_goals/storage/sheets_storage.py
priv_goals/utils/__init__.py
priv_goals/utils/args_parser.py
priv_goals/utils/key_storage.py
priv_goals/utils/logger.py
priv_goals-0.0.5.dist-info/METADATA
priv_goals-0.0.5.dist-info/WHEEL
priv_goals-0.0.5.dist-info/entry_points.txt
priv_goals-0.0.5.dist-info/licenses/LICENSE
priv_goals-0.0.5.dist-info/RECORD
