Metadata-Version: 2.4
Name: priv-goals
Version: 0.0.5
Summary: A privacy-focused goal tracking application
Project-URL: Homepage, https://github.com/hesreallyhim/priv-goals
Project-URL: Repository, https://github.com/hesreallyhim/priv-goals.git
Project-URL: Documentation, https://github.com/hesreallyhim/priv-goals#readme
Project-URL: Bug Tracker, https://github.com/hesreallyhim/priv-goals/issues
Author-email: Really Him <hesreallyhim@proton.me>
License: Copyright (C) 2024 Really Him
License-File: LICENSE
Keywords: ai,goals,personal-development,privacy,productivity,task-management
Classifier: Development Status :: 3 - Alpha
Classifier: Environment :: Web Environment
Classifier: Intended Audience :: End Users/Desktop
Classifier: License :: OSI Approved :: GNU Affero General Public License v3
Classifier: Operating System :: OS Independent
Classifier: Programming Language :: Python
Classifier: Programming Language :: Python :: 3
Classifier: Programming Language :: Python :: 3.8
Classifier: Programming Language :: Python :: 3.9
Classifier: Programming Language :: Python :: 3.10
Classifier: Programming Language :: Python :: 3.11
Classifier: Topic :: Office/Business
Classifier: Topic :: Utilities
Requires-Python: >=3.8
Requires-Dist: gradio>=4.0.0
Requires-Dist: gspread>=5.0.0
Requires-Dist: inquirer>=3.1.0
Requires-Dist: litellm>=1.0.0
Requires-Dist: oauth2client>=4.1.3
Requires-Dist: pyyaml>=6.0.0
Provides-Extra: dev
Requires-Dist: black; extra == 'dev'
Requires-Dist: pylint; extra == 'dev'
Requires-Dist: pytest; extra == 'dev'
